phlights/__init__.py
phlights/constants.py
phlights/flightsearch.py
phlights/flightsearchbuilder.py
phlights/util.py
phlights/errors/__init__.py
phlights/errors/configuration_error.py
phlights/models/__init__.py
phlights/models/flight.py
phlights/models/leg.py
phlights/models/trip.py
phlights-0.2.0.dist-info/LICENSE
phlights-0.2.0.dist-info/METADATA
phlights-0.2.0.dist-info/WHEEL
phlights-0.2.0.dist-info/top_level.txt
phlights-0.2.0.dist-info/RECORD
